turkish_suffix_library/__init__.py
turkish_suffix_library/consonants.py
turkish_suffix_library/database.db
turkish_suffix_library/sample_verbs_list.py
turkish_suffix_library/test_verbs.py
turkish_suffix_library/turkish.py
turkish_suffix_library/turkish_class.py
turkish_suffix_library/turkish_string.py
turkish_suffix_library-1.0.7.dist-info/LICENCE
turkish_suffix_library-1.0.7.dist-info/METADATA
turkish_suffix_library-1.0.7.dist-info/WHEEL
turkish_suffix_library-1.0.7.dist-info/top_level.txt
turkish_suffix_library-1.0.7.dist-info/RECORD
