Metadata-Version: 2.1
Name: turkish-suffix-library
Version: 1.0.7
Summary: Turkish suffix library
Home-page: https://github.com/miklagard/Turkish-Suffix-Library
Author: Cem Yildiz
Author-email: cem.yildiz@ya.ru
License: UNKNOWN
Platform: UNKNOWN
Classifier: Programming Language :: Python :: 3
Classifier: License :: OSI Approved :: MIT License
Classifier: Operating System :: OS Independent
Requires-Python: >=3.6
